{"root_group":{"name":"","path":"","id":"d41d8cd98f00b204e9800998ecf8427e","groups":[],"checks":[{"name":"score 200","path":"::score 200","id":"ae8c9e24b6d310bfa365d7857af41cbb","passes":120001,"fails":0}]},"options":{"summaryTimeUnit":"","noColor":false,"summaryTrendStats":["avg","med","p(95)","p(99)","max"]},"state":{"isStdOutTTY":false,"isStdErrTTY":false,"testRunDurationMs":30004.447496},"metrics":{"explain_found":{"contains":"default","values":{"rate":1,"passes":60129,"fails":0},"type":"rate"},"http_req_failed":{"type":"rate","contains":"default","values":{"rate":0,"passes":0,"fails":227666},"thresholds":{"rate<0.05":{"ok":true}}},"http_req_blocked":{"type":"trend","contains":"time","values":{"max":3.671855,"avg":0.0012278281254119907,"med":0.000875,"p(95)":0.00175,"p(99)":0.002875}},"http_req_waiting":{"contains":"time","values":{"max":6.443413,"avg":0.1832063018676487,"med":0.106412,"p(95)":0.6054237499999996,"p(99)":1.0282497999999987},"type":"trend"},"data_sent":{"contains":"data","values":{"count":34252813,"rate":1141591.192591244},"type":"counter"},"vus_max":{"type":"gauge","contains":"default","values":{"value":200,"min":200,"max":200}},"http_req_tls_handshaking":{"type":"trend","contains":"time","values":{"avg":0,"med":0,"p(95)":0,"p(99)":0,"max":0}},"vus":{"type":"gauge","contains":"default","values":{"value":15,"min":3,"max":22}},"checks":{"type":"rate","contains":"default","values":{"rate":1,"passes":120001,"fails":0}},"http_req_duration":{"type":"trend","contains":"time","values":{"p(95)":0.6603907499999999,"p(99)":1.0779740999999998,"max":6.611572,"avg":0.20472891169959304,"med":0.123995}},"explain_wait":{"values":{"max":11.49191,"avg":4.164534049925944,"med":5.0967459999999996,"p(95)":5.5837936,"p(99)":6.01623952},"type":"trend","contains":"time"},"explain_poll_misses":{"type":"counter","contains":"default","values":{"count":47536,"rate":1584.2984612976857}},"http_req_connecting":{"type":"trend","contains":"time","values":{"avg":0.00009416144703205574,"med":0,"p(95)":0,"p(99)":0,"max":0.837425}},"http_req_receiving":{"type":"trend","contains":"time","values":{"p(95)":0.038291,"p(99)":0.3139750499999998,"max":6.084427,"avg":0.015624048153875093,"med":0.005874}},"score_latency":{"type":"trend","contains":"time","values":{"p(99)":1.172579,"max":6.611572,"avg":0.2478659096590846,"med":0.159077,"p(95)":0.747887}},"iteration_duration":{"type":"trend","contains":"time","values":{"max":12.64246,"avg":2.64003517503191,"med":0.597476,"p(95)":6.847146,"p(99)":7.588659}},"iterations":{"type":"counter","contains":"default","values":{"count":120001,"rate":3999.4404168247975}},"explain_latency":{"type":"trend","contains":"time","values":{"p(95)":0.6546077999999997,"p(99)":1.1331969999999998,"max":6.49191,"avg":0.2116993112807455,"med":0.12937}},"data_received":{"contains":"data","values":{"count":73442186,"rate":2447709.9939864194},"type":"counter"},"http_reqs":{"type":"counter","contains":"default","values":{"count":227666,"rate":7587.7417849587455}},"http_req_duration{expected_response:true}":{"type":"trend","contains":"time","values":{"p(95)":0.6603907499999999,"p(99)":1.0779740999999998,"max":6.611572,"avg":0.20472891169959304,"med":0.123995}},"http_req_sending":{"type":"trend","contains":"time","values":{"med":0.002458,"p(95)":0.009792,"p(99)":0.084163,"max":4.382786,"avg":0.00589856167807252}}}}